hf_download/__init__.py
hf_download/downloader.py
hf_download-1.0.dist-info/LICENSE
hf_download-1.0.dist-info/METADATA
hf_download-1.0.dist-info/WHEEL
hf_download-1.0.dist-info/entry_points.txt
hf_download-1.0.dist-info/top_level.txt
hf_download-1.0.dist-info/RECORD
