Metadata-Version: 2.1
Name: hf-download
Version: 1.0
Summary: A tool to download models from Hugging Face
Home-page: https://github.com/jfk/huggingface_downloader
Author: jfk
Author-email: fumikazu.kiyota@gmail.com
License: UNKNOWN
Platform: UNKNOWN
Classifier: Programming Language :: Python :: 3
Classifier: License :: OSI Approved :: MIT License
Classifier: Operating System :: OS Independent
Requires-Python: >=3.6
Requires-Dist: huggingface-hub
